drvn/installer/__init__.py
drvn/installer/_dotfile_repository.py
drvn/installer/_logging.py
drvn/installer/_script.py
drvn/installer/_utils.py
drvn/installer/installer.py
drvn/installer/installers/__init__.py
drvn/installer/installers/duplicity_installer.py
drvn/installer/installers/tmux_installer.py
drvn/installer/installers/ultimate_vim_installer.py
drvn.installer-0.3.7.dist-info/LICENCE
drvn.installer-0.3.7.dist-info/METADATA
drvn.installer-0.3.7.dist-info/WHEEL
drvn.installer-0.3.7.dist-info/entry_points.txt
drvn.installer-0.3.7.dist-info/top_level.txt
drvn.installer-0.3.7.dist-info/RECORD
