Metadata-Version: 2.1
Name: drvn.installer
Version: 0.3.7
Summary: UNKNOWN
Home-page: https://github.com/hallgrimur1471/drvn_installer
Author: Hallgrimur David Egilsson
Author-email: hallgrimur1471@gmail.com
License: UNKNOWN
Platform: UNKNOWN
Classifier: Programming Language :: Python :: 3.7
Classifier: Programming Language :: Python :: 3.8
Classifier: Operating System :: POSIX :: Linux
Requires-Python: >=3.7
